README.rst
setup.cfg
setup.py
timeflow/__init__.py
timeflow/cli.py
timeflow/main.py
timeflow/settings.py
timeflow/stats.py
timeflow/utils.py
timeflow.egg-info/PKG-INFO
timeflow.egg-info/SOURCES.txt
timeflow.egg-info/dependency_links.txt
timeflow.egg-info/entry_points.txt
timeflow.egg-info/top_level.txt