Metadata-Version: 1.0
Name: timeflow
Version: 0.2.5
Summary: Small CLI time logger
Home-page: https://github.com/trimailov/timeflow
Author: Justas Trimailovas
Author-email: j.trimailovas@gmail.com
License: MIT
Keywords: timelogger,logging,timetracker,tracker
Platform: UNKNOWN
